responsemock/__init__.py
responsemock/entry.py
responsemock/utils.py
pytest_responsemock-1.1.1.dist-info/AUTHORS
pytest_responsemock-1.1.1.dist-info/LICENSE
pytest_responsemock-1.1.1.dist-info/METADATA
pytest_responsemock-1.1.1.dist-info/WHEEL
pytest_responsemock-1.1.1.dist-info/entry_points.txt
pytest_responsemock-1.1.1.dist-info/top_level.txt
pytest_responsemock-1.1.1.dist-info/RECORD
